ecommerce
kernel
sage_cache
