Metadata-Version: 2.1
Name: django-sage-cache
Version: 0.1.1
Summary: queryset caching for Django
Home-page: https://github.com/sageteam-org/django-sage-cache
Author: Sage Team
Author-email: mail@sageteam.org
License: GNU
Download-URL: https://github.com/sageteam-org/django-sage-cache/archive/refs/tags/0.1.0.tar.gz
Keywords: django,python,cache,SQL,queryset
Platform: UNKNOWN
Classifier: Environment :: Web Environment
Classifier: Framework :: Django
Classifier: Framework :: Django :: 3.2
Classifier: Framework :: Django :: 3.1
Classifier: Intended Audience :: Developers
Classifier: License :: OSI Approved :: GNU Affero General Public License v3
Classifier: Operating System :: OS Independent
Classifier: Programming Language :: Python
Classifier: Programming Language :: Python :: 3
Classifier: Programming Language :: Python :: 3 :: Only
Classifier: Programming Language :: Python :: 3.6
Classifier: Programming Language :: Python :: 3.7
Classifier: Programming Language :: Python :: 3.8
Classifier: Programming Language :: Python :: 3.9
Classifier: Topic :: Internet :: WWW/HTTP
Classifier: Topic :: Internet :: WWW/HTTP :: Dynamic Content
Requires-Python: >=3.5
License-File: LICENSE
License-File: AUTHORS.md
